<?xml version="1.0" encoding="UTF-8" standalone="no"?>
<pk><wd nm="le&apos;s" rd="199,0:3009,3073,4262,4325|271,0:2848,2911,4074,4137"/><wd nm="le1" rd="217,0:1430,2581|275,0:1410,2561|326,0:8111"/><wd nm="le2" rd="140,0:3836|217,0:5341,6564|275,0:5299,6517|326,0:8118"/><wd nm="le2img" rd="148,0:2863|161,0:3066"/><wd nm="le2pdf" rd="148,0:2947|161,0:3140"/><wd nm="le3" rd="326,0:8125"/><wd nm="le_basicdbexample" rd="211,0:1477|278,0:1538,1870"/><wd nm="le_chart" rd="99,0:1426,2792,2852,3092,3538,3747,4053,4103,4542,4638,4664,7591,10812,11006,11406|105,0:3650,3678"/><wd nm="le_controller" rd="97,0:587|98,0:489,703,6509|99,0:859|100,0:851|105,0:622,7470"/><wd nm="le_data" rd="100,0:2202"/><wd nm="le_default" rd="212,0:949|279,0:941"/><wd nm="le_detailed" rd="212,0:3190|279,0:3521"/><wd nm="le_example" rd="105,0:1236,2185,2258,2654,2926,3134,3223"/><wd nm="le_fc_print_manager" rd="99,0:26804"/><wd nm="le_fc_print_manager_js" rd="99,0:11863,27167"/><wd nm="le_mode" rd="99,0:10223,18952"/><wd nm="le_mscharts" rd="211,0:7967|278,0:8141"/><wd nm="le_multiseries" rd="276,0:3069"/><wd nm="le_series" rd="98,0:739,828,1804,5229"/><wd nm="le_singleseries" rd="209,0:874|276,0:908"/><wd nm="le_tables_data" rd="105,0:4277"/><wd nm="le_type2" rd="145,0:444|159,0:444"/><wd nm="lead" rd="107,0:2719,4808|115,0:2752,4643|173,0:4940"/><wd nm="leading" rd="101,0:5707,5836|288,0:3657,3839"/><wd nm="leads" rd="129,0:7168|312,0:7315"/><wd nm="leaks" rd="296,0:5701"/><wd nm="lean" rd="14,0:400|19,0:5513,11585,11896,13518,13800,14091,14374,14796,15168,21181,21586,22012|27,0:9097,9408|43,0:4029|44,0:1105|45,0:10628|46,0:5398,6351,6885,7099,7645,7799,7902,8701,8806,8899,9262,9378,9618,9902,10333,10918,11136,14455,14674,16153,16412,17388,18066,19626,20209,20385,20850,21138,21715,21955,22710,25328,25798,28190,28456,33460,33560,33657,35979,36331,38328,38414,38647,38986|47,0:4833,5788,6317,7249,7358,7468,7618,7981,8097,8338,8384,8668,9099,9684,9902,10605,13440,14944,15484,15743,17503,18086,18262,18845,19085,19840,22458,22928,25320,25586,30925,31025,31122,32342,32694,34691,34777,35010|48,0:6356,7311,7841,8177,8723,8877,8980,10349,10457,10837,11196,11318,11445,11572,12487,12716,13247,13538,13845,14275,14493,14714,14820,15864,18699,19955,20508,21396,22035,23204,23537,24105,24498,24736,24901,25224,25942,26624,26682,27283,27742,27837,28273,28621,28978,29327,29767,30212,32472,32636,38069,38539,39031,41643,41911,42146,46494,47242,47349,47423,48712,48777,48855,49137,49259,51762,53405,53491,53724,54063,55500,55733|49,0:5456,6409,6943,7159,7705,7859,7962,8761,9376,9471,9621,9984,10100,10341,10395,10679,11161,11265,11850,12055,12288,12991,15441,15495,15664,17170,17311,17796,18537,20100,20612,20745,21260,21943,22001,22588,22699,23158,23253,23689,23929,24684,27302,27772,30164,30432,30672,35801,37336,37688,39890,40573,40790,41812,43739,44582,46628,46711,47050|50,0:4862,5815,6344,6890,7044,7147,7946,8051,8146,8296,8659,8775,9016,9065,9349,9780,10365,10583,13902,14121,15627,16173,16432,18195,18778,18954,19543,19783,20538,23162,23638,26030,26296,31723,31823,31920,33140,33492,35489,35575,35808,36147|51,0:4355,5314,5843,6389,6543,6646,7445,7550,7645,7795,8158,8274,8515,8564,8848,9330,9434,10019,10237,13181,13235,13394,13613,15119,15430,16356,16868,17001,17534,17774,18529,21147,21617,24009,24275,29702,29802,30972,31324,33321,33554,33893|52,0:6796,7749,8283,8502,8648,9194,9348,9451,10250,10865,10960,11110,11473,11589,11830,11884,12168,12599,13184,13402,14105,16940,18445,18990,19230,20259,21000,22563,23146,23322,23893,24575,24633,25220,25331,25790,25885,26321,26561,27316,29934,30404,32796,33064,33304,38604,40139,40491,42237,43116,43790,43855,44072,46878,47536,49749,49835,50068,50407|53,0:6635,7594,8128,8347,8493,9039,9193,9296,10095,10710,10805,10955,11318,11434,11549,11630,11707,12068,12122,12406,13466,13673,13887,14264,15004,17839,19344,19890,20130,21159,21900,23463,24047,24242,24427,24998,25680,25738,26325,26436,26895,26990,27426,27666,28421,28585,31701,32171,32662,33353,33601,36848,37116,37356,42658,44193,44545,46227,47106,47780,47845,48062,51412,52070,53858,53944,54177|54,0:4617,4857,6387,6921,7135,7223,7926,8289,8405,8510,9287,9505,10553,12924,14425,14513,15031,15240,15377,18167,18477,18720,18934,19874,21188,22667,22908,23084,23574,23635,24295,24353,25191,25286,25722,25962,26717,29335,29805,32197,32465,32705,36437,38218,38283,41350|55,0:1870,2830,3361,3484,3565,3627,3680,3827,4586,6886,8392,8718,8816,10081,10955,11014,11152,11489,12021,12584,12824,13579,16197,17697,18696,18764,19391,19502,20164,20412,20678,23421,23982,24117|56,0:1818,2771,3302,3425,3506,3568,3621,3768,4527,6821,8327,8653,9794,10784,10843,10981,11539,12071,12634,12874,13629,16247,17747,18746,18814,19441,19552,20214,20462,20728,22516,23725|57,0:5080,6039,6573,6787,7333,7487,7590,8389,9004,9097,9460,9576,9817,10101,10532,11117,11335,14654,14873,16375,16610,17351,18914,19497,19673,20138,20426,20636,21090,21330,22085,24703,25173,27565,27831,32831,32931,33550,35872,36224,38221,38307,38540,38879|58,0:4747,5708,6237,6783,6937,7040,7839,7944,8037,8400,8516,8757,8811,9234,9526,10157,10267,10372,10483,11186,14021,15524,15783,17542,17875,18544,18838,19194,19252,19839,20316,20749,20989,21753,24370,24840,27230,27498,27739,32349,34194,34546,36650,36706,36771,37605,37741,40436,40522,40605,40944|59,0:6071,7025,7559,7773,8319,8473,8576,9375,9480,9573,9936,10052,10293,10347,10631,11062,11647,11865,12568,15403,16906,17165,18539,20098,20681,20857,21322,21610,22170,22851,22909,23496,23607,24066,24161,24597,24837,25592,28210,28680,31070,31338,31579,36287,37823,38175,40088,40144,40209,40284,41241,43138,43274,45488,45574,45807,46146|60,0:5506,6459,6988,7920,8029,8139,8289,8652,8768,9009,9063,9486,9778,10363,10581,11284,14119,15621,16160,16419,18175,18758,18934,19500,20181,20239,20826,20937,21396,21491,21927,22167,22922,25540,26010,28400,28668,28909,33951,35550,35902,37991,38047,38112,39821,39957,41627,41713,41946|61,0:5295,6248,6777,7709,7818,7928,8078,8482,8536,8820,9251,9887,10181,10399,11102,13552,13606,13775,15275,15410,16500,17027,17199,17661,18342,18400,18987,19098,19557,19652,20088,20328,21092,23709,24179,26569,26837,27078,32112,33711,34063,35901,35966,36614,39418,39651|62,0:6161,7114,7643,8189,8343,8446,9250,9464,10079,10172,10535,10651,10891,11179,11260,11527,11631,11857,12665,12872,13086,13197,13623,13856,13960,14700,17150,17204,17373,18879,19020,19505,20246,21809,22337,22532,22713,23174,23856,23914,24501,24612,25071,25166,25602,25842,26597,26761,29877,30347,30838,31529,31777,35024,35292,35532,40661,42196,42548,44755,45438,45655,46677,47541,49202,51462,51695|63,0:5532,6485,7014,7560,7714,7817,8616,8721,8816,8966,9329,9445,9686,9740,10024,10455,11040,11258,11963,14798,16301,16847,17106,18866,19449,19625,20198,20879,20937,21524,21635,22094,22189,22627,22867,23622,26240,26710,29102,29370,29611,34741,36278,36630,38720,38776,38841,40551,40687,42358,42444,42677,43016|64,0:5324,6277,6806,7352,7506,7609,8408,8513,8608,8758,9121,9237,9478,9532,9816,10298,10402,10987,11205,11910,14360,14414,14583,16087,16398,17324,17836,17911,18486,19167,19225,19812,19923,20382,20477,20915,21155,21910,24528,24998,27390,27658,27899,33029,34566,34918,36757,36822,38532,40153,40386,40725|65,0:6064,7017,7551,7765,8311,8465,8568,9367,9982,10075,10438,10554,10795,10849,11133,11564,12149,12367,13072,15907,17585,18324,19887,20175,20625,21208,21384,21606,22044,22726,22784,23371,23482,23941,24036,24475,24715,25470,28088,28558,30950,31218,31459,36167,37704,38056,39430,40049,40723,40784,43681,45069,46554,46640,46873,47212|66,0:5804,6757,7286,7832,7986,8089,8888,8993,9086,9449,9565,9806,9860,10144,10566,10751,11356,11464,11560,11640,12343,15178,16683,17229,17488,19251,19834,20010,20580,21261,21319,21906,22033,22492,22587,23023,23263,24018,26636,27106,29498,29766,30002,34938,36469,36821,39097,39153,39218,40912,41048,42713,42799,43032,43371|67,0:6530,7489,8023,8237,8783,8937,9040,9839,10457,10820,10936,11051,11132,11200,11385,11746,11800,12084,12254,13245,13459,13836,14576,17411,18916,19462,19721,20873,21614,23177,23761,23956,24141,24712,25394,25452,26039,26166,26625,26720,27156,27396,28151,28315,31415,31885,32376,33001,33249,36496,36764,37004,41944,43479,43831,45435,46372,47046,48754,50141,50629,50982,51170,51423,52799,54083,55571,55657,55890|68,0:4418,5371,5905,6119,6665,6819,6922,7721,8352,8447,8597,8931,9047,9162,9243,9449,9498,9782,10213,10816,11279,11461,11537,14893,15112,16617,17162,17421,18573,19314,20878,21461,21637,22226,22466,23221,25839,26309,27154,29565,29831,35258,35358,35455,36819,37171,39168,39254,39487|69,0:4337,5290,5824,6014,6560,6714,6817,7616,8246,8341,8491,8854,8970,9085,9166,9372,9421,9705,10187,10291,10894,11357,11539,11615,11706,11939,14959,15013,15172,15391,16897,17382,17653,18264,19828,20355,20527,21006,21246,22001,24619,25089,25934,28345,28611,34139,34239,35553,35905,37902,38135|70,0:1830,2783,3314,3437,3518,3580,3633,3780,4539,8052,8375,8437,9521,10169,10228,10366,10992,11524,12087,12327,13082,15700,17200,18160,18228,18855,18966,19628,19876,20142,22032,23222,23566|71,0:1779,2732,3263,3386,3467,3529,3582,3729,4488,8001,8327,9248,10233,10292,10430,11056,11588,12151,12391,13146,15764,17269,18229,18297,18924,19035,19653,19901,20167,21981,23190|72,0:7875,8828,9357,9903,10057,10160,11526,11634,12014,12375,12463,12585,12712,12838,13752,14259,14550,14857,15287,15505,15726,15832,16369,17072,19907,21163,21716,23152,23893,25456,25789,26357,26750,26988,27297,27476,28195,28876,28934,29521,29632,30091,30186,30622,30970,31327,31676,32116,32561,34821,34985,40418,40888,41380,43991,44259,44495,49031,49779,49886,49960,51241,51306,51381,52332,52649,52994,53116,55148,56591,56677,56910,57249,58686,58919|73,0:6503,7462,7996,8210,8756,8910,9013,9812,9917,10010,10373,10489,10601,11573,11627,11911,12084,12286,12433,13136,15971,17477,17736,19787,21163,21451,21901,22484,22660,23229,23910,23968,24555,24666,25125,25220,25656,25896,26660,29277,29747,32139,32407,32642,37339,38869,39221,41139,41195,41260,41575,42292,44442,44578,46047,46385,47246,47332|74,0:5974,6927,7456,8002,8156,8259,9058,9163,9258,9408,9771,9887,10128,10182,10605,10897,11482,11684,11831,12534,15369,16874,17419,17678,19927,20510,20686,21255,21936,21994,22581,22692,23151,23246,23682,23922,24686,27303,27773,30165,30433,30668,35786,37316,37668,39762,39818,39883,40699,40835,42852,43315,43401,43634|75,0:6950,7903,8437,8656,8802,9348,9502,9605,10404,11019,11114,11264,11627,11743,11984,12038,12461,12753,13338,13540,13687,14390,17225,18730,19275,19515,20544,21771,23334,23917,24093,24816,25498,25556,25989,26100,26559,26654,27090,27330,28094,30711,31181,33573,33841,34076,39295,40825,41177,43020,43642,44316,44381,44456,47951,48609,50273,50359,50592,50931|76,0:6501,7454,7988,8207,8353,8899,9053,9156,9955,10570,10665,10815,11178,11294,11409,11490,11699,11983,12286,12347,13326,13533,13747,14108,14255,14995,17830,19335,19880,20120,21149,22376,23939,24523,24718,24903,25472,26154,26212,26799,26910,27369,27464,27900,28140,28904,29068,32183,32653,33144,33835,34083,37329,37597,37832,43049,44579,44931,46613,47492,48166,48231,48306,50890,51548,54082,54168,54401|77,0:6500,7453,7987,8201,8747,8901,9004,9803,10418,10511,10874,10990,11102,12074,12128,12412,12585,12787,12934,13637,16472,18152,19379,20702,21032,21320,21770,22353,22529,23098,23780,23838,24425,24536,24995,25090,25526,25766,26530,29147,29617,32009,32277,32512,37209,38739,39091,41009,41683,41748,41823,44701,45359,46936,47190,47276,47509|78,0:6013,6966,7495,8041,8195,8298,9097,9202,9295,9658,9774,10015,10076,10663,10760,11044,11470,11605,11703,11788,11867,12570,15405,16910,17455,17714,19963,20546,20722,21291,21972,22030,22617,22744,23203,23298,23734,23974,24738,27355,27825,30217,30485,30720,35838,37368,37720,39814,39870,39935,40751,40887,42794,42880,43113,43452|79,0:5268,6221,6750,7682,7791,7901,8051,8326,9361,9415,9699,9870,10156,10242,10350,10446,10526,11229,13679,13733,13902,15405,15540,16634,17161,17333,17793,18474,18532,19119,19246,19705,19800,20236,20476,21240,23857,24327,26719,26987,27223,32095,33689,34041,35884,35949,36587,39367,39600|80,0:6060,7013,7547,7761,8307,8461,8564,9363,9468,9561,9924,10040,10281,10335,10619,11050,11655,11763,11859,11939,12642,15477,16983,17242,18617,20183,20471,20921,21504,21680,22250,22931,22989,23576,23703,24162,24257,24693,24933,25688,28306,28776,31168,31436,31672,36186,37717,38069,39987,40043,40108,40186,40449,43022,43158,45367,45453,45686,46025|81,0:5349,6302,6831,7763,7872,7980,8343,8459,8700,8754,9177,9460,9558,10163,10271,10367,10447,11150,13961,15466,16011,16270,18033,18616,18792,19356,20037,20095,20682,20809,21268,21363,21799,22039,22793,25411,25881,28273,28541,28777,33640,35234,35586,37680,37736,37801,39495,39631,41296,41382,41615|82,0:5507,6460,6989,7535,7689,7792,8591,8696,8789,9152,9268,9509,9563,9847,10269,10373,10978,11086,11182,11262,11965,14800,16302,16847,17106,18865,19448,19624,20191,20872,20930,21517,21644,22103,22198,22634,22874,23629,26247,26717,29107,29375,29611,34547,36078,36430,38524,38580,38645,40339,40475,42140,42226,42459,42798|83,0:5180,6133,6662,7208,7362,7465,8269,8483,9098,9191,9554,9670,9911,9965,10249,10671,10775,11382,12085,14920,16425,16970,17229,18992,19575,19751,20322,21004,21062,21649,21776,22235,22330,22766,23006,23761,26379,26849,29241,29509,29749,34936,36471,36823,39042,39716,39781,41629,42287,43956,44042,44275,44614|84,0:5296,6249,6778,7324,7478,7581,8380,8485,8578,8941,9057,9298,9352,9636,10118,10213,10317,10922,11030,11126,11206,11909,14359,14413,14582,16088,16229,17325,17852,18024,18484,19165,19223,19810,19937,20396,20491,20927,21167,21922,24540,25010,27402,27670,27906,32842,34373,34725,36568,36633,38327,39942,40175,40514|85,0:4978,5931,6460,7006,7160,7263,8067,8281,8896,8989,9352,9468,9709,9763,10047,10529,10624,10728,11335,12038,14488,14542,14711,16217,16358,17454,17981,18153,18614,19295,19353,19940,20067,20526,20621,21057,21297,22052,24670,25140,27532,27800,28040,33226,34761,35113,37081,37764,39612,41753,41986,42325|86,0:5120,6073,6602,7148,7302,7405,8209,8423,9038,9131,9494,9610,9850,10138,10219,10486,10590,10816,11635,11849,11960,12386,12619,12723,13460,13530,15980,16034,16203,17709,17850,18335,19076,20639,21167,21358,21539,22000,22682,22740,23327,23454,23913,24008,24444,24684,25439,25603,28719,29189,29680,30371,30619,33866,34134,34374,39561,41096,41448,43655,44338,44555,45577,46441,48102,50362,50595|87,0:63582,64116,64330,64876,65030,65132,65747,65841,66539,66599,66772,66978,67492,67872,68186,68621,69357,72192,74742,75810,77556,78816,79399,79575,80148,80819,80877,81464,81565,82004,82439,82679,83409,85172,85642,88034,88188,93719,94398,95045,95115,97576,98270,99423,99677,99763,99996|89,0:6180,6291|110,0:1155,1239,1456|118,0:917|123,0:1428|133,0:1932|134,0:2697|136,0:1458,1635|144,0:281|152,0:227,307,859,1970|154,0:1991,2197,2450,3091|155,0:1281,2350|156,0:526,2517,3351,6299,6615,6927|157,0:281|185,0:295,541,1072|229,0:1717,6420,24321,24803,25437|248,0:669,2398,6408,24540,24561,25423,26033|291,0:8806|297,0:1848,1941|298,0:15787,15955,21488,22456,23818,24750,25308|303,0:392|311,0:4341|313,0:1447|314,0:3460,3566"/></pk>