<?xml version="1.0" encoding="UTF-8" standalone="no"?>
<pk><wd nm="nate" rd="16,0:7386,7581,7715|19,0:13019,13103,13185|27,0:4050,4261,4363,7691,7754,10531,10615,10697|42,0:1022,1224,1322,1543,1604|46,0:3411,18953,19261,20410,20483,20564,21163,21231,21300|47,0:16827,17138,18287,18358,18437|48,0:4045,22528,22839,23562,23635,23716,24523,24606,24695|49,0:19424,19735|50,0:3138,17519,17830,18979,19052,19133|51,0:15680,15991|52,0:4968,21887,22198,23347,23420,23501|53,0:4807,22787,23098,24452,24525,24606|54,0:21849,22155,23109,23182|55,0:9659|56,0:9693|57,0:3093,18238,18549,19698,19771,19852,20451,20519,20588|58,0:2765,16871,17179,17900,17973,18054|59,0:3970,19427,19735,20882,20955,21036,21635,21703,21772|60,0:17504,17812,18959,19030,19109|61,0:15831,16139|62,0:21133,21444|63,0:3703,18195,18503,19650,19723,19804|64,0:16649,16960|65,0:3961,19213,19521,20200,20268,20337,21409,21482,21563|66,0:3976,18575,18886,20035,20108,20189|67,0:4702,22501,22812,24166,24239,24320|68,0:2694,20202,20513,21662,21735,21816|69,0:2623,19151,19462|70,0:9420|71,0:9147|72,0:5564,24780,25091,25814,25887,25968,26775,26858,26947|73,0:3842,20484,20795,21476,21544,21613,22685,22758,22839|74,0:3574,19251,19562,20711,20784,20865|75,0:4550,22658,22969,24118,24191,24272|76,0:4101,23263,23574,24928,25001,25082|77,0:3842,20266,20577,21345,21413,21482,22554,22627,22708|78,0:3613,19287,19598,20747,20820,20901|79,0:15960,16271|80,0:3959,19504,19815,20496,20564,20633,21705,21778,21859|81,0:17357,17668,18817,18888,18967|82,0:3679,18194,18502,19649,19722,19803|83,0:3352,18316,18627,19776,19849,19930|84,0:16649,16960|85,0:16778,17089|86,0:19963,20274|87,0:78245,78543,79600,79673,79754|88,0:6847|122,0:10271,10412|129,0:199|154,0:3122,3278|169,0:8632|175,0:208|185,0:1753,1834,1893|187,0:5520|202,0:5183|209,0:6493|236,0:724,2297|255,0:694,2191|260,0:5626|276,0:6117|312,0:227|321,0:7139,7224,7349,7421|326,0:5947"/><wd nm="natebandcolor" rd="154,0:3214"/><wd nm="natebandcolors" rd="154,0:3322"/><wd nm="natecolorbands" rd="154,0:3067"/><wd nm="nated" rd="48,0:27409|49,0:22825|52,0:25457|53,0:26562|59,0:23733|60,0:21063|61,0:19224|62,0:24738|63,0:21761|64,0:20049|65,0:23608|66,0:22159|67,0:26292|72,0:29758|73,0:24792|74,0:22818|75,0:26226|76,0:27036|77,0:24662|78,0:22870|79,0:19372|80,0:23829|81,0:20935|82,0:21770|83,0:21902|84,0:20063|85,0:20193|86,0:23580|87,0:81691"/><wd nm="natehgridalpha" rd="46,0:20512|48,0:23664|50,0:19081|52,0:23449|53,0:24554|57,0:19800|58,0:18002|59,0:20984|63,0:19752|65,0:21511|66,0:20137|67,0:24268|68,0:21764|72,0:25916|73,0:22787|74,0:20813|75,0:24220|76,0:25030|77,0:22656|78,0:20849|80,0:21807|82,0:19751|83,0:19878|87,0:79702"/><wd nm="natehgridcolor" rd="27,0:4182,4215,4414|46,0:20361,20446|48,0:23513,23598|50,0:18930,19015|52,0:23298,23383|53,0:24403,24488|54,0:23060,23145|57,0:19649,19734|58,0:17851,17936|59,0:20833,20918|63,0:19601,19686|65,0:21360,21445|66,0:19986,20071|67,0:24117,24202|68,0:21613,21698|72,0:25765,25850|73,0:22636,22721|74,0:20662,20747|75,0:24069,24154|76,0:24879,24964|77,0:22505,22590|78,0:20698,20783|80,0:21656,21741|82,0:19600,19685|83,0:19727,19812|87,0:79551,79636|304,0:3175,3201"/><wd nm="nately" rd="1,0:6750,6787|18,0:8157,8194,9677,9712|27,0:4108|42,0:1076|46,0:13354,13389|47,0:12329,12364|48,0:12795,17588,17623|49,0:14715,14750|50,0:12801,12836|51,0:12455,12490|52,0:15829,15864|53,0:16728,16763|54,0:12277,12312|55,0:6310,6345|56,0:6245,6280|57,0:13553,13588|58,0:12910,12945|59,0:14292,14327|60,0:13008,13043|61,0:12826,12861|62,0:16424,16459|63,0:13687,13722|64,0:13634,13669|65,0:14796,14831|66,0:14067,14102|67,0:16300,16335|68,0:13792,13827|69,0:14233,14268|70,0:6263,6298|71,0:6212,6247|72,0:18796,18831|73,0:14860,14895|74,0:14258,14293|75,0:16114,16149|76,0:16719,16754|77,0:15361,15396|78,0:14294,14329|79,0:12953,12988|80,0:14366,14401|81,0:12850,12885|82,0:13689,13724|83,0:13809,13844|84,0:13633,13668|85,0:13762,13797|86,0:15254,15289|87,0:71081,71116|291,0:22437,22474"/><wd nm="naterowbgalpha" rd="185,0:1852"/><wd nm="naterowbgcolor" rd="185,0:1791|236,0:771,2337|255,0:739,2229"/><wd nm="nates" rd="304,0:2680"/><wd nm="natevgridalpha" rd="19,0:13130|27,0:4436,10642|42,0:1393,1496|46,0:21265|47,0:18385|48,0:24633|57,0:20553|59,0:21737|60,0:19057|65,0:20302|72,0:26885|73,0:21578|77,0:21447|80,0:20598|81,0:18915"/><wd nm="natevgridcolor" rd="19,0:12966,13053|27,0:10478,10565|42,0:1147,1180,1371,1441,1468,1853|46,0:21114,21197|47,0:18238,18321|48,0:24462,24557|57,0:20402,20485|59,0:21586,21669|60,0:18910,18993|65,0:20151,20234|72,0:26714,26809|73,0:21427,21510|77,0:21296,21379|80,0:20447,20530|81,0:18768,18851|122,0:10578"/><wd nm="nating" rd="136,0:779"/><wd nm="nation" rd="0,0:1107|16,128:0,30,65,310,658,5437,9698,10373,12522,14025|19,0:7575|24,0:1107|25,0:3343|29,0:73|40,0:251|48,0:50946,51928|49,128:21,76,497,547,605,20938,30447,34903,35409,36784,39255,40637,42274,42384,42923,44412,47812|52,128:11,56,462,502,550,3118,8549,23571,33079,37706,38212,39587,42068,43919,45413,45523,46062,47737,51159|53,128:7,48,452,488,532,2448,8394,24676,37131,41760,42266,43641,47909,49403,49513,50596,52271,55070|54,128:0,56,544,584,633,2948,9721,14862,23252,32480,35539,36045,38347,38666,38776,42037|55,0:17759|56,0:17809|61,0:37198|62,128:29,92,523,581,647,22852,35307,39763,40269,41644,44111,44205,45502,47139,47249,48386,49875,52610|67,128:36,106,629,688,761,24390,36779,41046,41552,42927,45499,47289,47399,47938,49427,52328,53468,56812|75,128:6,48,475,512,557,8703,42754,51679|76,128:6,55,491,535,587,8254,55293|83,128:26,86,509,564,627,20000,29524,34038,34544,35919,39845,40164,40274,40813,42488,45381|85,128:26,86,509,564,627,18292,27815,32328,32834,34209,37828,38147,38257,38796,40285,43093|86,128:24,82,513,566,627,21678,34149,38663,39169,40544,43011,43105,44402,46039,46149,47286,48775,51505|88,0:2403,6832,7112|89,0:6482|90,0:14249|91,0:5243|94,0:3346|95,0:5574|98,0:6576|104,0:4989|106,128:0,22,44,197,228,331,629,700,739,2094,2443,3566,3599,3732,3762,4169,4199,4645,5276|108,0:1077,1733,1939,2958,3025|109,0:1473|110,0:3000,3018,3039,3119,3152,3258,3419,3754|112,0:797|114,128:0,21,42,196,227,330,642,681,2355,2742,4162,4194,4341,4371,4813,4841,5346,5841|116,0:1281,1932,3220,3286|117,0:1741|118,0:3035,3053,3074,3132,3164,3270,3430,3760|119,0:2306,4670|120,0:1120|123,0:3840|129,0:69435|134,0:2859|136,0:2030|138,0:4612|155,0:1727|165,0:756|169,0:4311,5521|170,128:17,52,429,1340,1921,1982,2319,4156,4877,7591|175,0:5125,5142|179,0:154|182,0:10224|187,0:1447,2265,3617,5505,5758|188,0:1235,1261,8912,20930,21032,21500,24485|190,0:4710|191,0:1643,2462|193,0:7694|196,0:5912,6717|202,0:1395,2247,5168,5430|203,0:5950|205,0:3786|206,0:1678,2563|207,0:2484|208,0:2783,7325|209,0:1979,2736,4469,6478,6748|210,0:1273,1297,24454,24558,25048,28035|212,0:4804|213,0:1684,2590|215,0:4342,8176|223,0:1362|227,128:32,58,76,199,391,940,1151,2328,2569,2785,2891,3253,4651,4812|228,0:4744,4797,4855,4924,4982,5052,5120,5190,5243,5296,5355|229,0:8045,8912,9852,18544,18634,18796,18895,19006,19342,20808,22579,22814|242,0:1360|246,128:32,58,76,199,391,949,1068,2343,2656,2979,4340,4502|247,0:4289,4342,4400,4469,4527,4597,4665,4735,4788,4841,4900|248,0:8042,8924,9844,18592,18683,18852,18959,19072,19417,21103,22834,23072|257,0:822|259,0:485|260,0:1551,2345,3811,5611,5864|261,0:1251,1277,8873,20838,20940,21408,24397,24443|263,0:4854|264,0:1627,2410|266,0:7475|268,0:5696,6495|276,0:2673,4198,6102,6375|277,0:1286,1312,23945,24049,24538,27526|279,0:5316|280,0:1611,2460|282,0:4356,8228|284,0:1285,1336,1415,1725,2338,2398|287,0:2762,2813,2892,3202,3812,3868|288,0:835,2778|289,0:630|291,0:1317,21084,23082,27972,31175|293,0:225,1432,1484,1564,1878,2496,2553,2741|294,0:628|295,0:2744,2796,2876,3190,3812,3869,4058|296,0:4760,4854,5013,9740,9905,13652,13666,13759,13794,13880,13925,13972,14015,14060,14103,14146,14191,14234,14270,14729,18171|297,0:15706|299,0:774|301,0:56|303,0:58|312,0:17337,20025,23523,27377|313,0:2561|321,0:1778,1905|327,0:3399"/><wd nm="nations" rd="1,0:5619|6,0:4965|18,0:7053|32,0:4954|291,0:38503|309,0:1523,1967|321,0:255,2600|324,0:209"/><wd nm="native" rd="0,0:1789|11,0:346|24,0:1775|36,0:372|45,0:1973|89,0:27609|122,0:8560|156,0:2779|178,0:1591|188,0:15671|195,0:1279|197,0:9793|201,0:1298|210,0:19725|218,0:1280|257,0:733|261,0:15567|267,0:1280|269,0:9400|273,0:1286|277,0:19221|283,0:1294|291,0:8581|313,0:1219|314,0:686"/><wd nm="natively" rd="35,0:479"/><wd nm="natory" rd="19,0:25085,25270|326,0:3449"/><wd nm="nature" rd="0,0:3399|12,0:3727,4862|24,0:4188|124,0:2628,8543,8576|156,0:2629,6401|287,0:4378|295,0:4529|297,0:3121,3128,3809,3816,4460,5079,5555,6069|298,0:201,21628,21671,21796,25479,25532,25683,25720,25769,25824|299,0:2255|306,0:307|309,0:2128|313,0:2253"/><wd nm="navailability" rd="36,0:2637"/><wd nm="navbuttoncolor" rd="185,0:2382"/><wd nm="navbuttonhovercolor" rd="185,0:2466"/><wd nm="navbuttonpadding" rd="185,0:2681"/><wd nm="navbuttonradius" rd="185,0:2285"/><wd nm="navigation" rd="68,0:621,962|69,0:603,919|185,0:584,2258,2329,2413,2507,2763,2783|186,0:3256"/><wd nm="navigator" rd="131,0:1886,2033"/><wd nm="naware" rd="117,0:1974"/><wd nm="nazzy" rd="233,0:234|252,0:238"/><wd nm="nbgcolor" rd="154,0:4602"/><wd nm="nbordercolor" rd="138,0:12257|142,0:8762|143,0:1931|154,0:4090,4473,4708,4799,5518,5713,5818"/><wd nm="nborderthickness" rd="154,0:5833"/><wd nm="nbsp" rd="89,0:13381,13627|99,0:6515,6762|102,0:2828,2946,3070,3197,3320,3431,3527,3548|104,0:8745,8884|311,0:6668,6682,6688,6779,6793,6799,6890,6904,6910,7001,7015,7021,7118,7124,7233,7239,7871,7885,7891,7982,7996,8002,8093,8107,8113,8204,8218,8224,8321,8327,8435,8441"/><wd nm="nc" rd="12,0:3972,3995,4702,4725,4799"/><wd nm="ncapsulated" rd="173,0:4825|301,0:7831"/><wd nm="ncapsulation" rd="173,0:4872"/><wd nm="ncaption" rd="291,0:30284,30435,30560,30701"/><wd nm="ncate" rd="6,0:2033|32,0:2029"/><wd nm="ncated" rd="0,0:1581,1698,1845|6,0:9206|9,0:3250|24,0:1579,1697,1831,1889|32,0:9190|33,0:10636|36,0:2418,2555|46,0:7696|47,0:7067,7321|48,0:8774|49,0:7756,36111,36178|50,0:6941|51,0:6440|52,0:9245,38914,38981|53,0:9090,42968,43035|54,0:36747,36814|55,0:11585,11963,12062|56,0:11635,12013,12112|57,0:7384|58,0:6834,32659,32726|59,0:8370,36597,36664|60,0:7738,7992,34261,34328|61,0:7527,7781,32422,32489|62,0:8240,40971,41038|63,0:7611,35051,35118|64,0:7403,33339,33406|65,0:8362,36477,36544|66,0:7883,35248,35315|67,0:8834,42254,42321|68,0:6716|69,0:6611|70,0:11088,11466,11565|71,0:11152,11530,11629|72,0:9954|73,0:8807,37649,37716|74,0:8053,36096,36163|75,0:9399,39605,39672|76,0:8950,43359,43426|77,0:8798,37519,37586|78,0:8092,36148,36215|79,0:7500,7754,32405,32472|80,0:8358,36496,36563|81,0:7581,7835,33950,34017|82,0:7586,34857,34924|83,0:7259,35246,35313|84,0:7375,33152,33219|85,0:7057,33536,33603|86,0:7199,39871,39938|87,0:64927|122,0:12406|291,0:29541,36589|296,0:11913,11948,12044"/></pk>